stash_pr_stats/__init__.py
stash_pr_stats/stash_pr_stats.py
stash_pr_stats-0.0.5.dist-info/LICENSE
stash_pr_stats-0.0.5.dist-info/METADATA
stash_pr_stats-0.0.5.dist-info/WHEEL
stash_pr_stats-0.0.5.dist-info/entry_points.txt
stash_pr_stats-0.0.5.dist-info/top_level.txt
stash_pr_stats-0.0.5.dist-info/RECORD
