Metadata-Version: 2.1
Name: stash-pr-stats
Version: 0.0.5
Summary: Get pr stats from stash (bitbucket server)
Home-page: https://github.com/noahp/stash-pr-stats
Author: Noah Pendleton
Author-email: 2538614+noahp@users.noreply.github.com
License: UNKNOWN
Platform: UNKNOWN
Classifier: License :: OSI Approved :: MIT License
Classifier: Programming Language :: Python :: 2.7
Classifier: Programming Language :: Python :: 3.6
Classifier: Operating System :: OS Independent
Requires-Dist: click
Requires-Dist: pygal
Requires-Dist: stashy (==0.6)
Requires-Dist: tabulate
Requires-Dist: tqdm
